Workbook

Sheet Executive Overview
A1: OVALENS: CAPSTONE MASTER FEATURE & ENDPOINT CHECKLIST
A2: Foundation University (CCS) • Team DevIn • DSRM + Agile Framework • Two-Tier Agent Architecture
B4: Total Items | D4: Completed [Done] | F4: In Progress | H4: Pending Backlog
B5: =COUNTA('Master Checklist'!A4:A150) | D5: =COUNTIF('Master Checklist'!H4:H150, "Done") | F5: =COUNTIF('Master Checklist'!H4:H150, "In Progress") | H5: =COUNTIF('Master Checklist'!H4:H150, "Backlog")
A8: Subsystem Domain | B8: Scope & Description | C8: Total Tasks | D8: Done | E8: Completion %
A9: Backend REST API | B9: All FastAPI routers: Auth, Batches, Scans, Analytics, Reports, Settings, Users | C9: =COUNTIF('Master Checklist'!C4:C150, "Backend API") | D9: =COUNTIFS('Master Checklist'!C4:C150, "Backend API", 'Master Checklist'!H4:H150, "Done") | E9: =D9/C9
A10: Edge CV & Sorter App | B10: Camera grabber, YOLOv8 ONNX, SQLite WAL, cradle tracker, CustomTkinter 60 FPS | C10: =COUNTIF('Master Checklist'!C4:C150, "Edge CV") | D10: =COUNTIFS('Master Checklist'!C4:C150, "Edge CV", 'Master Checklist'!H4:H150, "Done") | E10: =D10/C10
A11: Dashboard Web Portal | B11: React 18 + Vite + TS: Tray matrix, batches, analytics, user admin, audit logs | C11: =COUNTIF('Master Checklist'!C4:C150, "Dashboard") | D11: =COUNTIFS('Master Checklist'!C4:C150, "Dashboard", 'Master Checklist'!H4:H150, "Done") | E11: =D11/C11
A12: Firmware & Hardware | B12: ESP32 Dev Module, optical interrupts, stepper indexed transport, servo diverters | C12: =COUNTIF('Master Checklist'!C4:C150, "Firmware") | D12: =COUNTIFS('Master Checklist'!C4:C150, "Firmware", 'Master Checklist'!H4:H150, "Done") | E12: =D12/C12
A13: AI Model & Dataset | B13: 3,000+ Itik Pinas dataset, 70/15/15 split, training, ONNX FP16 slim, benchmarks | C13: =COUNTIF('Master Checklist'!C4:C150, "AI & Data") | D13: =COUNTIFS('Master Checklist'!C4:C150, "AI & Data", 'Master Checklist'!H4:H150, "Done") | E13: =D13/C13
A14: Research & Docs | B14: Capstone manuscript (Chapters 1-6), APA citations, thesis defense preparation | C14: =COUNTIF('Master Checklist'!C4:C150, "Docs & Plan") | D14: =COUNTIFS('Master Checklist'!C4:C150, "Docs & Plan", 'Master Checklist'!H4:H150, "Done") | E14: =D14/C14
A17: Global Automated Workflow Rules:
A18: 1. Two-Tier Agent Architecture: Antigravity orchestrates, plans, audits, and commits; Codex implements features and tests.
A19: 2. Automated Quality Gate: Every feature MUST pass backend pytest (13 tests), edge pytest (8 tests), and dashboard build.
A20: 3. Automated Checklist Sync: Running 'python scripts/verify_and_commit.py --task <TASK_ID> -m "..."' marks the item Done here and in PROJECT_PLAN.md.
A21: 4. Strict Architectural Tenets: Zero Firebase (100% FastAPI+PostgreSQL), offline SQLite WAL at edge, 3 biological classes, FU branding (#800000).

Sheet Master Checklist
A3: Task ID | B3: DSRM Phase | C3: Subsystem | D3: Feature / Endpoint | E3: Technical Specification & Acceptance Criteria | F3: Diagram Reference | G3: Role | H3: Status | I3: Priority | J3: Automated Test / Verification
A4: TASK-DOC-01 | B4: Phase 1: Planning | C4: Docs & Plan | D4: Authentic Manuscript Integration | E4: Parse DevIn (2026).md into Chapters 1-6 with 15 APA 7 citations and Title/Approval Sheet | F4: Manuscript 00-06 | G4: Antigravity | H4: Done | I4: P0 - Critical | J4: docs/manuscript/*.md review
A5: TASK-DOC-02 | B5: Phase 1: Planning | C5: Docs & Plan | D5: Import & Catalog Academic Diagrams | E5: Embed and convert IPO Matrix, DSRM Methodology, System Flowchart, and Use Case diagrams (.drawio & .html) | F5: All 4 Diagrams | G5: Antigravity | H5: Done | I5: P0 - Critical | J5: docs/diagrams catalog audit
A6: TASK-DOC-03 | B6: Phase 1: Planning | C6: Docs & Plan | D6: Two-Tier Agent Workflow & Quality Gate | E6: Establish Antigravity + Codex partnership, PROJECT_PLAN.md, CHANGELOG.md, and verify_and_commit.py | F6: PROJECT_PLAN.md | G6: Antigravity | H6: Done | I6: P0 - Critical | J6: python scripts/verify_and_commit.py
A7: TASK-NEW-SCOPE-01 | B7: Phase 4: Development | C7: Cross-System | D7: Day 10 Binary Domain Refactor | E7: Standardize backend, edge, dashboard, firmware, tests, and docs on Day 10 with FERTILE/INFERTILE outcomes | F7: System-wide contract | G7: Codex | H7: Done | I7: P0 - Critical | J7: pytest + npm.cmd run build
A8: TASK-BE-AUTH-01 | B8: Phase 4C: Backend | C8: Backend API | D8: POST /api/v1/auth/login | E8: JWT authentication endpoint with bcrypt password verification and role extraction | F8: Use Case: Worker | G8: Codex | H8: Done | I8: P0 - Critical | J8: test_login_and_me
A9: TASK-BE-AUTH-02 | B9: Phase 4C: Backend | C9: Backend API | D9: GET /api/v1/auth/me | E9: Retrieve current authenticated user profile, permissions, and active status | F9: Use Case: Worker | G9: Codex | H9: Done | I9: P0 - Critical | J9: test_login_and_me
A10: TASK-BE-AUTH-03 | B10: Phase 4C: Backend | C10: Backend API | D10: POST /api/v1/auth/register | E10: Account registration endpoint with default Candling Worker role | F10: Use Case: Admin | G10: Codex | H10: Done | I10: P1 - High | J10: test_rbac_and_admin_security_protections
A11: TASK-BE-USR-01 | B11: Phase 4C: Backend | C11: Backend API | D11: GET /api/v1/users | E11: List all system users with role filters (Worker, Supervisor, Admin) | F11: Use Case: Admin | G11: Codex | H11: Done | I11: P1 - High | J11: test_rbac_and_admin_security_protections
A12: TASK-BE-USR-02 | B12: Phase 4C: Backend | C12: Backend API | D12: POST /api/v1/users | E12: Admin user creation endpoint with RBAC role assignment | F12: Use Case: Admin | G12: Codex | H12: Done | I12: P1 - High | J12: test_rbac_and_admin_security_protections
A13: TASK-BE-USR-03 | B13: Phase 4C: Backend | C13: Backend API | D13: PATCH /api/v1/users/{id}/status | E13: Toggle user active/deactivated state to revoke credentials | F13: Use Case: Admin | G13: Codex | H13: Done | I13: P1 - High | J13: test_rbac_and_admin_security_protections
A14: TASK-BE-USR-04 | B14: Phase 4C: Backend | C14: Backend API | D14: PATCH /api/v1/users/me/profile | E14: Allow authenticated user to update their display name and email | F14: Use Case: Worker | G14: Codex | H14: Done | I14: P2 - Medium | J14: test_user_profile_and_password_change_flow
... A127: TASK-NEW-FW-INSTALL-01 | B127: Phase 5: Firmware | C127: Firmware | D127: Install three-board v3 firmware | E127: Explicit user approval with empty conveyor; identify old firmware; rebuild and upload COM5/7/9; verify flash hashes, v3 roles and paused/lamp-off telemetry. Physical sorting remains untested. | F127: docs/EDGE_THREE_BOARD_IMPLEMENTATION.md | G127: Codex | H127: Done | I127: P1 - High | J127: Three ESP32 builds; three verified uploads; actual application discovery and boot telemetry
